pytablut/__init__.py
pytablut/__main__.py
pytablut/client.py
pytablut/py.typed
pytablut/rules.py
pytablut/server.py
pytablut/strategy.py
pytablut/utils.py
pytablut-0.1.2.dist-info/METADATA
pytablut-0.1.2.dist-info/WHEEL
pytablut-0.1.2.dist-info/entry_points.txt
pytablut-0.1.2.dist-info/licenses/LICENSE
pytablut-0.1.2.dist-info/RECORD
