Metadata-Version: 2.4
Name: pytablut
Version: 0.1.2
Summary: Tablut Game Implementation in Python
Author-email: Jinqi Wei <changshanshi@outlook.com>
License-File: LICENSE
Requires-Python: >=3.12
Requires-Dist: click>=8.1.8
Requires-Dist: numpy>=2.3.4
Requires-Dist: pydantic>=2.12.4
Requires-Dist: sharklog>=0.1.1
Requires-Dist: timevery>=0.1.9
